[
  {
    "title": "ガソリン 激変緩和措置始まる 約1～2週間で小売価格反映見込み",
    "link": "http://www3.nhk.or.jp/news/html/20260319/k10015079001000.html",
    "source": "NHK",
    "image": ""
  },
  {
    "title": "イラン ガス田に攻撃受け カタールのLNG施設を攻撃",
    "link": "http://www3.nhk.or.jp/news/html/20260319/k10015079031000.html",
    "source": "NHK",
    "image": ""
  },
  {
    "title": "NY原油市場 先物価格 一時1バレル＝100ドル超に",
    "link": "http://www3.nhk.or.jp/news/html/20260319/k10015079221000.html",
    "source": "NHK",
    "image": ""
  },
  {
    "title": "高市首相 アメリカに到着 20日未明にトランプ大統領と首脳会談",
    "link": "http://www3.nhk.or.jp/news/html/20260319/k10015079371000.html",
    "source": "NHK",
    "image": ""
  },
  {
    "title": "日銀 金融政策維持を決定 イラン情勢受け判断か",
    "link": "http://www3.nhk.or.jp/news/html/20260319/k10015079411000.html",
    "source": "NHK",
    "image": ""
  },
  {
    "title": "イラン情勢で農家のコスト増懸念 激変緩和措置などで対応へ",
    "link": "http://www3.nhk.or.jp/news/html/20260319/k10015079421000.html",
    "source": "NHK",
    "image": ""
  },
  {
    "title": "「楽天市場」アカウント乗っ取りなど被害の相談約400件 注意を",
    "link": "http://www3.nhk.or.jp/news/html/20260319/k10015079471000.html",
    "source": "NHK",
    "image": ""
  }
]
